LICENSE.txt
MANIFEST.in
README.md
requirements.txt
setup.cfg
setup.py
chatgpt_to_powerpoint/__init__.py
chatgpt_to_powerpoint/__main__.py
chatgpt_to_powerpoint/jsonSchema.py
chatgpt_to_powerpoint.egg-info/PKG-INFO
chatgpt_to_powerpoint.egg-info/SOURCES.txt
chatgpt_to_powerpoint.egg-info/dependency_links.txt
chatgpt_to_powerpoint.egg-info/requires.txt
chatgpt_to_powerpoint.egg-info/top_level.txt
chatgpt_to_powerpoint/langchainHandler/__init__.py
chatgpt_to_powerpoint/powerpointGenerator/__init__.py
chatgpt_to_powerpoint/slideLayout/__init__.py