Metadata-Version: 2.1
Name: chatgpt-to-powerpoint
Version: 0.1.2
Summary: create automatically powerpoint with chatgpt
Home-page: https://github.com/jeremyjouvancedev/chatgpt-to-powerpoint
Author: Jeremy Jouvance
Author-email: jeremy.jouvance@gmail.com
Keywords: chatgpt,powerpoint,creation
Classifier: Development Status :: 3 - Alpha
Classifier: Intended Audience :: Developers
Classifier: Topic :: Software Development :: Build Tools
Classifier: License :: OSI Approved :: MIT License
Classifier: Programming Language :: Python :: 3
Classifier: Programming Language :: Python :: 3.4
Classifier: Programming Language :: Python :: 3.5
Classifier: Programming Language :: Python :: 3.6
License-File: LICENSE.txt
